{
  "success": true,
  "message": "搜索「6147 護城河 競爭優勢」找到 10 条结果，展示前 5 条：\n\n**1. [什么是护城河? - 知乎](https://zhuanlan.zhihu.com/p/456047184)** — 知乎 (2022-01-11 19:35:00)\n   护城河-企业的持续性竞争优势 持续性:不能今天有,明天就没有了 竞争优势:比竞争对手更强的地方 护城河的五种类型:1､无形资产:品牌､专利､拍照;品牌的典型表现为:定价权 专利的典型表现为:无替代品 拍照的典型表现为:垄断 2､成本优势;通过降低生产成本为自己的业务构筑经济护城河 3､高转换成本;客户更换服务商时付出的成本;例如苹果转换安卓 4､网络效应;使用的客户越来越多,价值随之提升 5､有效...\n\n**2. [护城河的三种竞争优势_知乎](https://zhuanlan.zhihu.com/p/29513433)** — 知乎 (2017-09-20 17:18:00)\n   1:低成本优势“比如:沃尔玛” 2:优秀的产品和服务,差异化竞争优势 3:大品牌,其产品和服务在消费者心目中占有很大的位置,产品和服务对消费者具有很强的粘性｡\n\n**3. [阅读《企业的护城河:打造基业长青的竞争优势》 - 今日头条](https://www.toutiao.com/article/7482940474433536564/)** — 今日头条 (2025-03-18 08:32:00)\n   (1)护城河是一家企业拥有的其他企业难以复制､难以撼动的优势,是企业建立起来的一种可持续的竞争优势｡ 护城河的存在能够助力企业抵御竞争对手的侵袭,维持长期稳定竞争优势,在商业竞争中立于不败之地,从而持续获取超额收益,实现长期可持续发展(基业长青)｡ (2)巴菲特说: “我们以加宽护城河的能力以及不可攻击性作为判断一家伟大企业的主要标准｡” \n\n**4. [睿远基金APP读书会第二期推荐的格林沃尔德教授的《竞争优势:透视企业护城河》,读后感触颇深,先讲讲建立优势竞争。_财富号_东方财富网](https://caifuhao.eastmoney.com/news/20230509142154121321400)** — 财富号东方财富网 (2023-05-09 14:21:00)\n   只要存在于市场,就会有竞争｡一家企业要发展,就要建立自己的竞争优势,并且不断地去发挥自己的竞争优势,使之成为自己企业的护城河｡然后不断地去扩展自己的市场份额,把对手挤出市场竞争行列,也让新进入者加大竞争的成本｡ 每一家企业在发展期间,都需要定战略｡而战略的规划,找准自己的企业定位,建立自己的市场竞争优势｡是发自己独有的技术,建立技术壁垒,做好产品;还是发展市场规模,快速的扩展市场占有率;\n\n**5. [《竞争优势:透视企业护城河》最触动我的,是对“护城河不是静态壁垒,而是动态竞争优_富国中证港股通互联网ETF发起式联接C(of014674)股吧_东方财...](http://gubaf10.eastmoney.com/news,of014674,1542120267.html)** (2025-04-21 22:09:10)\n   现有 282 人阅读过该帖,评论 0 条 #洞见阅读会# 《竞争优势:透视企业护城河》最触动我的,是对“护城河不是静态壁垒,而是动态竞争优势”的深刻阐释｡书中强调,真正的护城河不仅是短期领先,更是让对手难以复制的“价值创造系统”,这需要从客户需求､成本结构､网络生态等多维度动态评估,护城河不是静态的,更是一个稳定的持续的创新的护城河稳定系统｡ \n\n> 还有 5 条结果未展示，完整数据已包含在搜索结果中供分析使用。",
  "data": {
    "query": "6147 護城河 競爭優勢",
    "totalResults": 10,
    "docs": [
      {
        "passage": "护城河-企业的持续性竞争优势 持续性:不能今天有,明天就没有了 竞争优势:比竞争对手更强的地方 护城河的五种类型:1､无形资产:品牌､专利､拍照;品牌的典型表现为:定价权 专利的典型表现为:无替代品 拍照的典型表现为:垄断 2､成本优势;通过降低生产成本为自己的业务构筑经济护城河 3､高转换成本;客户更换服务商时付出的成本;例如苹果转换安卓 4､网络效应;使用的客户越来越多,价值随之提升 5､有效规模;",
        "score": 0.36107793,
        "date": "2022-01-11 19:35:00",
        "title": "什么是护城河? - 知乎",
        "url": "https://zhuanlan.zhihu.com/p/456047184",
        "site": "知乎",
        "images": [
          "https://pic3.zhimg.com/v2-6f840fe6864b1df104fefec9dbade0a2_r.jpg"
        ],
        "favicon": "http://img04.sogoucdn.com/app/a/200913/227e8153170b79598ec7048fb37f2c3f.png"
      },
      {
        "passage": "1:低成本优势“比如:沃尔玛” 2:优秀的产品和服务,差异化竞争优势 3:大品牌,其产品和服务在消费者心目中占有很大的位置,产品和服务对消费者具有很强的粘性｡",
        "score": 0.2640582,
        "date": "2017-09-20 17:18:00",
        "title": "护城河的三种竞争优势_知乎",
        "url": "https://zhuanlan.zhihu.com/p/29513433",
        "site": "知乎",
        "images": [],
        "favicon": "http://img04.sogoucdn.com/app/a/200913/227e8153170b79598ec7048fb37f2c3f.png"
      },
      {
        "passage": "(1)护城河是一家企业拥有的其他企业难以复制､难以撼动的优势,是企业建立起来的一种可持续的竞争优势｡ 护城河的存在能够助力企业抵御竞争对手的侵袭,维持长期稳定竞争优势,在商业竞争中立于不败之地,从而持续获取超额收益,实现长期可持续发展(基业长青)｡ (2)巴菲特说: “我们以加宽护城河的能力以及不可攻击性作为判断一家伟大企业的主要标准｡” ",
        "score": 0.2604073,
        "date": "2025-03-18 08:32:00",
        "title": "阅读《企业的护城河:打造基业长青的竞争优势》 - 今日头条",
        "url": "https://www.toutiao.com/article/7482940474433536564/",
        "site": "今日头条",
        "images": [
          "https://p26-sign.toutiaoimg.com/tos-cn-i-axegupay5k/3325e88ccd8047d8ba42c74e191e621b~tplv-tt-origin-web:gif.jpeg?_iz=58558&from=article.pc_detail&lk3s=953192f4&x-expires=1767333263&x-signature=86u5kGv3fC8lk9OU%2ByCWrIwh2eE%3D"
        ],
        "favicon": "http://img02.sogoucdn.com/app/a/200913/cbe956ef91c9f8564d5257e55bddd12e.png"
      },
      {
        "passage": "只要存在于市场,就会有竞争｡一家企业要发展,就要建立自己的竞争优势,并且不断地去发挥自己的竞争优势,使之成为自己企业的护城河｡然后不断地去扩展自己的市场份额,把对手挤出市场竞争行列,也让新进入者加大竞争的成本｡ 每一家企业在发展期间,都需要定战略｡而战略的规划,找准自己的企业定位,建立自己的市场竞争优势｡是发自己独有的技术,建立技术壁垒,做好产品;还是发展市场规模,快速的扩展市场占有率;",
        "score": 0.16133995,
        "date": "2023-05-09 14:21:00",
        "title": "睿远基金APP读书会第二期推荐的格林沃尔德教授的《竞争优势:透视企业护城河》,读后感触颇深,先讲讲建立优势竞争。_财富号_东方财富网",
        "url": "https://caifuhao.eastmoney.com/news/20230509142154121321400",
        "site": "财富号东方财富网",
        "images": [
          "https://g1.dfcfw.com/g4/202410/20241014110701.png"
        ],
        "favicon": ""
      },
      {
        "passage": "现有 282 人阅读过该帖,评论 0 条 #洞见阅读会# 《竞争优势:透视企业护城河》最触动我的,是对“护城河不是静态壁垒,而是动态竞争优势”的深刻阐释｡书中强调,真正的护城河不仅是短期领先,更是让对手难以复制的“价值创造系统”,这需要从客户需求､成本结构､网络生态等多维度动态评估,护城河不是静态的,更是一个稳定的持续的创新的护城河稳定系统｡ ",
        "score": 0.15649608,
        "date": "2025-04-21 22:09:10",
        "title": "《竞争优势:透视企业护城河》最触动我的,是对“护城河不是静态壁垒,而是动态竞争优_富国中证港股通互联网ETF发起式联接C(of014674)股吧_东方财...",
        "url": "http://gubaf10.eastmoney.com/news,of014674,1542120267.html",
        "site": "",
        "images": [
          "http://gbfek.dfcfw.com/project/guba/images/error/error_img_160.png"
        ],
        "favicon": ""
      },
      {
        "passage": "现有 190 人阅读过该帖,评论 0 条 #洞见阅读会# 《竞争优势:透视企业护城河》一书,让我对投资有了全新的认知｡书中核心观点指出,企业的“护城河”是抵御竞争对手､保障长期盈利的关键｡这意味着投资不能只关注当下业绩,更要评估企业的长期竞争力｡拥有强大品牌､专利技术､规模经济或网络效应的企业,如同筑起坚固壁垒,更易在市场波动中保持领先,为投资者创造长期价值｡ ",
        "score": 0.15376358,
        "date": "2025-04-29 10:50:58",
        "title": "《竞争优势:透视企业护城河》一书,让我对投资有了全新的认知。书中核心观点指出,企_富国中证港股通互联网ETF发起式联接C(of014674)股吧_东方财...",
        "url": "http://gubaf10.eastmoney.com/news,of014674,1545191499.html",
        "site": "",
        "images": [
          "http://gbfek.dfcfw.com/project/guba/images/error/error_img_160.png"
        ],
        "favicon": ""
      },
      {
        "passage": "如何在剧烈变革的行业格局中建立自己的护城河,从而维系持续性的竞争优势是所有传媒机构必须面对的问题｡本文在系统梳理企业护城河理论与持续性竞争优势理论的基础上,结合中国语境下传媒业实践,提出了传媒业如何搭建护城河的概念框架｡本研究的理论价值在于将西... (共5页) ",
        "score": 0.14949505,
        "date": "2026-01-28 04:12:52",
        "title": "传媒机构护城河搭建与持续性竞争优势研究-《当代传播》2020年01期-中国知网",
        "url": "https://mall.cnki.net/magazine/Article/DACB202001014.htm",
        "site": "中国知网",
        "images": [
          "https://c61.cnki.net/CJFD/big/DACB.jpg"
        ],
        "favicon": ""
      },
      {
        "passage": "今天致趣的 何润 师兄给我发了一个真假护城河的图,兴趣所致,就聊聊这个话题｡ 什么是企业的护城河,什么是竞争优势,这是创业者经常被人问到的问题,很难回答｡但确实很重要,我以前也经常在思考,壁垒､ 竞争优势 ､护城河经常被人大谈特谈,但是似乎没有什么区分,也很少有人讲明白｡ 个人之见,之前画了这个图表达自己对这个问题的理解｡ 有一句话很重要:护城河是结构性竞争优势! ",
        "score": 0.14554016,
        "date": "2021-11-10 23:58:00",
        "title": "论竞争优势、护城河和壁垒 - 知乎",
        "url": "https://zhuanlan.zhihu.com/p/431866959",
        "site": "知乎",
        "images": [
          "https://pic4.zhimg.com/v2-b8b95d28d8f725ad6c47524e20d53709_r.jpg"
        ],
        "favicon": "http://img04.sogoucdn.com/app/a/200913/227e8153170b79598ec7048fb37f2c3f.png"
      },
      {
        "passage": "优秀的企业需要护城河 , 护城河越宽越好 : · 护城河 : 品牌壁垒+工艺稀缺性+高端定价权 · 护城河 : 渠道垄断+成本控制+规模效应 · 护城河 : 医疗器械国产替代+全球化布局 · 护城河 : 动力电池技术壁垒+产业链整合 · 护城河 : 水电资源垄断+永续现金流 · 护城河 : 品牌壁垒+渠道控制+技术积累 · 护城河 : 零售银行龙头+财富管理优势 · 护城河 : 综合金融协同+科技赋能 · 护城河 : 创新药研发能力+专利壁垒 · 护城河 : 安防领域技术壁垒+规模效应 · 护城河 : 国家保密配方+稀缺原料供应 · 护城河 : 多元化产品矩阵+全球化布局 · 护城河 : 化工行业规模优势+技术壁垒 · 护城河 : 儿科用药独家品种+政策支持 · 护城河 : 全产业链布局+成本控制能力 - 护城河 : 社交网络效应+游戏/支付生态闭环 - 护城河 : 外卖市场垄断+本地生活服务网络 - 护城河 : 免税牌照壁垒+消费回流红利 - 护城河 : 饮用水品牌溢价+渠道渗透力 20. 港交所 ( 00388.HK ) - 护城河 : 资本市场枢纽地位+政策红利 - 护城河 : 品牌溢价+老年化趋势 - 护城河 : 工业自动化技术壁垒+国产替代 - 护城河 : 梯媒场景垄断+数字化投放能力 - 护城河 : 品牌溢价+中药产品全覆盖 - 护城河 : 半导体制造国产替代+产能优势 - 护城河 : 综合物流网络+品牌溢价 27. 中国建筑 ( 601668 ) - 护城河 : ",
        "score": 0.14410882,
        "date": "2025-03-01 09:39:00",
        "title": "优秀的企业需要护城河,护城河越宽越好:1. 贵州茅台 (600519)· 护城河:品牌壁垒工艺稀缺性高端定价权2. ... - 雪球",
        "url": "https://xueqiu.com/5324239224/325526487",
        "site": "雪球",
        "images": [
          "https://xqimg.imedao.com/19a0498f258369083fcf4ac6.png"
        ],
        "favicon": "http://img03.sogoucdn.com/app/a/200913/xueqiucom"
      },
      {
        "passage": "投入､新产品开发能力及其市场响应速度,是维持和强化竞争优势的关键｡ 4.品牌价值:品牌的影响力､知名度和忠诚度,能够为公司带来额外的竞争优势和市弛垒｡ 结合以上分析,我们可以洞察出相应的策略方向: 1. 深化市场渗透:通过提升产品质量和服务,巩固现有市场份额｡ 2. 拓展新领域:通过研发创新,拓展新的应用领域和市场份额｡ 3. 强化品牌建设:提升品牌影响力,增强消费者忠诚度｡ 4. ",
        "score": 0.13516441,
        "date": "2025-02-19 00:56:00",
        "title": "【技术分析】公司竞争优势之护城河分析与策略洞察",
        "url": "https://www.55188.com/thread-30670567-1-1.html",
        "site": "",
        "images": [],
        "favicon": ""
      }
    ],
    "requestId": "0721be3006ba40649faceff19df5d632"
  }
}